smog_usage_stats/__init__.py
smog_usage_stats/chaosStats.py
smog_usage_stats/search.py
smog_usage_stats/usageStats.py
smog_usage_stats/validator_util.py
smog_usage_stats-1.0.10.dist-info/LICENSE
smog_usage_stats-1.0.10.dist-info/METADATA
smog_usage_stats-1.0.10.dist-info/WHEEL
smog_usage_stats-1.0.10.dist-info/top_level.txt
smog_usage_stats-1.0.10.dist-info/RECORD
