Metadata-Version: 2.1
Name: smog_usage_stats
Version: 1.0.10
Author-email: "stu.gotz.dev" <gotz.stu.dev@gmail.com>
License: MIT License
Keywords: pokemon,usage,pokemon showdown,smogon
Classifier: License :: OSI Approved :: MIT License
Classifier: Intended Audience :: Developers
Classifier: Programming Language :: Python :: 3
Classifier: Operating System :: OS Independent
Requires-Python: >=3.7
License-File: LICENSE
Requires-Dist: beautifulsoup4==4.12.3
Requires-Dist: bs4==0.0.2
Requires-Dist: build==1.2.1
Requires-Dist: certifi==2024.7.4
Requires-Dist: charset-normalizer==3.3.2
Requires-Dist: colorama==0.4.6
Requires-Dist: idna==3.7
Requires-Dist: packaging==24.1
Requires-Dist: pyproject-hooks==1.1.0
Requires-Dist: requests==2.32.3
Requires-Dist: soupsieve==2.5
Requires-Dist: tomli==2.0.1
Requires-Dist: urllib3==2.2.2
Provides-Extra: dev
Requires-Dist: black; extra == "dev"
Requires-Dist: bumpver; extra == "dev"
Requires-Dist: isort; extra == "dev"
Requires-Dist: pip-tools; extra == "dev"
Requires-Dist: pytest; extra == "dev"
